[
    {
        "ID": 1,
        "motion": "",
        "weaponPrefabId": 101040002,
        "weaponBackDotName": "Dot_Wpn_swk_101040002",
        "weaponFrontDotName": "",
        "home3D": ""
    },
    {
        "ID": 2,
        "motion": "",
        "weaponPrefabId": 101040003,
        "weaponBackDotName": "Dot_Wpn_swk_101040003",
        "weaponFrontDotName": "",
        "home3D": ""
    },
    {
        "ID": 3,
        "motion": "",
        "weaponPrefabId": 101040004,
        "weaponBackDotName": "Dot_Wpn_swk_101040004",
        "weaponFrontDotName": "",
        "home3D": ""
    },
    {
        "ID": 4,
        "motion": "Fig_Unq_ki_Chr_529",
        "weaponPrefabId": 199999999,
        "weaponBackDotName": "",
        "weaponFrontDotName": "",
        "home3D": ""
    },
    {
        "ID": 5,
        "motion": "Fig_Unq_ki_Chr_530",
        "weaponPrefabId": 101040005,
        "weaponBackDotName": "Dot_Wpn_swk_101040005",
        "weaponFrontDotName": "",
        "home3D": ""
    },
    {
        "ID": 6,
        "motion": "",
        "weaponPrefabId": 101040006,
        "weaponBackDotName": "Dot_Wpn_swk_101040006",
        "weaponFrontDotName": "",
        "home3D": ""
    }
]