[
    {
        "ID": 1,
        "taskRewardPaymentLabel": 1,
        "rewardType": 20,
        "rewardID": 1,
        "rewardQuantity": 1,
        "paymentType": 0,
        "paymentID": 0,
        "paymentQuantity": 0
    },
    {
        "ID": 2,
        "taskRewardPaymentLabel": 2,
        "rewardType": 20,
        "rewardID": 2,
        "rewardQuantity": 1,
        "paymentType": 0,
        "paymentID": 0,
        "paymentQuantity": 0
    },
    {
        "ID": 3,
        "taskRewardPaymentLabel": 3,
        "rewardType": 20,
        "rewardID": 3,
        "rewardQuantity": 1,
        "paymentType": 0,
        "paymentID": 0,
        "paymentQuantity": 0
    },
    {
        "ID": 4,
        "taskRewardPaymentLabel": 4,
        "rewardType": 20,
        "rewardID": 34,
        "rewardQuantity": 1,
        "paymentType": 0,
        "paymentID": 0,
        "paymentQuantity": 0
    },
    {
        "ID": 5,
        "taskRewardPaymentLabel": 5,
        "rewardType": 20,
        "rewardID": 33,
        "rewardQuantity": 1,
        "paymentType": 0,
        "paymentID": 0,
        "paymentQuantity": 0
    }
]