[
    {
        "ID": 601011,
        "questType": 3,
        "obliviaeDetailId": 1,
        "questStageId": 601011,
        "mission": 6010111,
        "firstClearRewardGroupID": 749,
        "clearRewardGroupID": 750,
        "releaseConditionQuest": 0,
        "targetCommunicationGroup": 0,
        "targetCommunicationGroupCount": 0,
        "bossIcon": false
    },
    {
        "ID": 601021,
        "questType": 3,
        "obliviaeDetailId": 1,
        "questStageId": 601021,
        "mission": 6010211,
        "firstClearRewardGroupID": 751,
        "clearRewardGroupID": 752,
        "releaseConditionQuest": 601011,
        "targetCommunicationGroup": 0,
        "targetCommunicationGroupCount": 0,
        "bossIcon": false
    },
    {
        "ID": 601031,
        "questType": 3,
        "obliviaeDetailId": 1,
        "questStageId": 601031,
        "mission": 6010311,
        "firstClearRewardGroupID": 753,
        "clearRewardGroupID": 754,
        "releaseConditionQuest": 601021,
        "targetCommunicationGroup": 0,
        "targetCommunicationGroupCount": 0,
        "bossIcon": false
    },
    {
        "ID": 601041,
        "questType": 3,
        "obliviaeDetailId": 1,
        "questStageId": 601041,
        "mission": 6010411,
        "firstClearRewardGroupID": 755,
        "clearRewardGroupID": 756,
        "releaseConditionQuest": 601031,
        "targetCommunicationGroup": 0,
        "targetCommunicationGroupCount": 0,
        "bossIcon": false
    },
    {
        "ID": 601051,
        "questType": 3,
        "obliviaeDetailId": 1,
        "questStageId": 601051,
        "mission": 6010511,
        "firstClearRewardGroupID": 757,
        "clearRewardGroupID": 758,
        "releaseConditionQuest": 601041,
        "targetCommunicationGroup": 0,
        "targetCommunicationGroupCount": 0,
        "bossIcon": true
    },
    {
        "ID": 601061,
        "questType": 3,
        "obliviaeDetailId": 1,
        "questStageId": 601061,
        "mission": 6010611,
        "firstClearRewardGroupID": 759,
        "clearRewardGroupID": 760,
        "releaseConditionQuest": 601051,
        "targetCommunicationGroup": 0,
        "targetCommunicationGroupCount": 0,
        "bossIcon": false
    },
    {
        "ID": 601071,
        "questType": 3,
        "obliviaeDetailId": 1,
        "questStageId": 601071,
        "mission": 6010711,
        "firstClearRewardGroupID": 761,
        "clearRewardGroupID": 762,
        "releaseConditionQuest": 601061,
        "targetCommunicationGroup": 0,
        "targetCommunicationGroupCount": 0,
        "bossIcon": false
    },
    {
        "ID": 601081,
        "questType": 3,
        "obliviaeDetailId": 1,
        "questStageId": 601081,
        "mission": 6010811,
        "firstClearRewardGroupID": 763,
        "clearRewardGroupID": 764,
        "releaseConditionQuest": 601071,
        "targetCommunicationGroup": 0,
        "targetCommunicationGroupCount": 0,
        "bossIcon": false
    },
    {
        "ID": 601091,
        "questType": 3,
        "obliviaeDetailId": 1,
        "questStageId": 601091,
        "mission": 6010911,
        "firstClearRewardGroupID": 765,
        "clearRewardGroupID": 766,
        "releaseConditionQuest": 601081,
        "targetCommunicationGroup": 0,
        "targetCommunicationGroupCount": 0,
        "bossIcon": false
    },
    {
        "ID": 601101,
        "questType": 3,
        "obliviaeDetailId": 1,
        "questStageId": 601101,
        "mission": 6011011,
        "firstClearRewardGroupID": 767,
        "clearRewardGroupID": 768,
        "releaseConditionQuest": 601091,
        "targetCommunicationGroup": 0,
        "targetCommunicationGroupCount": 0,
        "bossIcon": true
    },
    {
        "ID": 601111,
        "questType": 3,
        "obliviaeDetailId": 1,
        "questStageId": 601111,
        "mission": 6011111,
        "firstClearRewardGroupID": 769,
        "clearRewardGroupID": 770,
        "releaseConditionQuest": 601101,
        "targetCommunicationGroup": 0,
        "targetCommunicationGroupCount": 0,
        "bossIcon": false
    },
    {
        "ID": 601121,
        "questType": 3,
        "obliviaeDetailId": 1,
        "questStageId": 601121,
        "mission": 6011211,
        "firstClearRewardGroupID": 771,
        "clearRewardGroupID": 772,
        "releaseConditionQuest": 601111,
        "targetCommunicationGroup": 0,
        "targetCommunicationGroupCount": 0,
        "bossIcon": false
    },
    {
        "ID": 601131,
        "questType": 3,
        "obliviaeDetailId": 1,
        "questStageId": 601131,
        "mission": 6011311,
        "firstClearRewardGroupID": 773,
        "clearRewardGroupID": 774,
        "releaseConditionQuest": 601121,
        "targetCommunicationGroup": 0,
        "targetCommunicationGroupCount": 0,
        "bossIcon": false
    },
    {
        "ID": 601141,
        "questType": 3,
        "obliviaeDetailId": 1,
        "questStageId": 601141,
        "mission": 6011411,
        "firstClearRewardGroupID": 775,
        "clearRewardGroupID": 776,
        "releaseConditionQuest": 601131,
        "targetCommunicationGroup": 0,
        "targetCommunicationGroupCount": 0,
        "bossIcon": false
    },
    {
        "ID": 601151,
        "questType": 3,
        "obliviaeDetailId": 1,
        "questStageId": 601151,
        "mission": 6011511,
        "firstClearRewardGroupID": 777,
        "clearRewardGroupID": 778,
        "releaseConditionQuest": 601141,
        "targetCommunicationGroup": 0,
        "targetCommunicationGroupCount": 0,
        "bossIcon": true
    },
    {
        "ID": 601161,
        "questType": 3,
        "obliviaeDetailId": 1,
        "questStageId": 601161,
        "mission": 6011611,
        "firstClearRewardGroupID": 779,
        "clearRewardGroupID": 780,
        "releaseConditionQuest": 601151,
        "targetCommunicationGroup": 1,
        "targetCommunicationGroupCount": 2,
        "bossIcon": false
    },
    {
        "ID": 601171,
        "questType": 3,
        "obliviaeDetailId": 1,
        "questStageId": 601171,
        "mission": 6011711,
        "firstClearRewardGroupID": 781,
        "clearRewardGroupID": 782,
        "releaseConditionQuest": 601161,
        "targetCommunicationGroup": 1,
        "targetCommunicationGroupCount": 2,
        "bossIcon": false
    },
    {
        "ID": 601181,
        "questType": 3,
        "obliviaeDetailId": 1,
        "questStageId": 601181,
        "mission": 6011811,
        "firstClearRewardGroupID": 783,
        "clearRewardGroupID": 784,
        "releaseConditionQuest": 601171,
        "targetCommunicationGroup": 1,
        "targetCommunicationGroupCount": 2,
        "bossIcon": false
    },
    {
        "ID": 601191,
        "questType": 3,
        "obliviaeDetailId": 1,
        "questStageId": 601191,
        "mission": 6011911,
        "firstClearRewardGroupID": 785,
        "clearRewardGroupID": 786,
        "releaseConditionQuest": 601181,
        "targetCommunicationGroup": 1,
        "targetCommunicationGroupCount": 4,
        "bossIcon": false
    },
    {
        "ID": 601201,
        "questType": 3,
        "obliviaeDetailId": 1,
        "questStageId": 601201,
        "mission": 6012011,
        "firstClearRewardGroupID": 787,
        "clearRewardGroupID": 788,
        "releaseConditionQuest": 601191,
        "targetCommunicationGroup": 1,
        "targetCommunicationGroupCount": 4,
        "bossIcon": true
    },
    {
        "ID": 601211,
        "questType": 3,
        "obliviaeDetailId": 1,
        "questStageId": 601211,
        "mission": 6012111,
        "firstClearRewardGroupID": 789,
        "clearRewardGroupID": 790,
        "releaseConditionQuest": 601201,
        "targetCommunicationGroup": 1,
        "targetCommunicationGroupCount": 4,
        "bossIcon": false
    },
    {
        "ID": 601221,
        "questType": 3,
        "obliviaeDetailId": 1,
        "questStageId": 601221,
        "mission": 6012211,
        "firstClearRewardGroupID": 791,
        "clearRewardGroupID": 792,
        "releaseConditionQuest": 601211,
        "targetCommunicationGroup": 1,
        "targetCommunicationGroupCount": 6,
        "bossIcon": false
    },
    {
        "ID": 601231,
        "questType": 3,
        "obliviaeDetailId": 1,
        "questStageId": 601231,
        "mission": 6012311,
        "firstClearRewardGroupID": 793,
        "clearRewardGroupID": 794,
        "releaseConditionQuest": 601221,
        "targetCommunicationGroup": 1,
        "targetCommunicationGroupCount": 6,
        "bossIcon": false
    },
    {
        "ID": 601241,
        "questType": 3,
        "obliviaeDetailId": 1,
        "questStageId": 601241,
        "mission": 6012411,
        "firstClearRewardGroupID": 795,
        "clearRewardGroupID": 796,
        "releaseConditionQuest": 601231,
        "targetCommunicationGroup": 1,
        "targetCommunicationGroupCount": 6,
        "bossIcon": false
    },
    {
        "ID": 601251,
        "questType": 3,
        "obliviaeDetailId": 1,
        "questStageId": 601251,
        "mission": 6012511,
        "firstClearRewardGroupID": 797,
        "clearRewardGroupID": 798,
        "releaseConditionQuest": 601241,
        "targetCommunicationGroup": 1,
        "targetCommunicationGroupCount": 8,
        "bossIcon": true
    },
    {
        "ID": 601261,
        "questType": 3,
        "obliviaeDetailId": 1,
        "questStageId": 601261,
        "mission": 6012611,
        "firstClearRewardGroupID": 799,
        "clearRewardGroupID": 800,
        "releaseConditionQuest": 601251,
        "targetCommunicationGroup": 1,
        "targetCommunicationGroupCount": 8,
        "bossIcon": false
    },
    {
        "ID": 601271,
        "questType": 3,
        "obliviaeDetailId": 1,
        "questStageId": 601271,
        "mission": 6012711,
        "firstClearRewardGroupID": 801,
        "clearRewardGroupID": 802,
        "releaseConditionQuest": 601261,
        "targetCommunicationGroup": 1,
        "targetCommunicationGroupCount": 8,
        "bossIcon": false
    },
    {
        "ID": 601281,
        "questType": 3,
        "obliviaeDetailId": 1,
        "questStageId": 601281,
        "mission": 6012811,
        "firstClearRewardGroupID": 803,
        "clearRewardGroupID": 804,
        "releaseConditionQuest": 601271,
        "targetCommunicationGroup": 1,
        "targetCommunicationGroupCount": 10,
        "bossIcon": false
    },
    {
        "ID": 601291,
        "questType": 3,
        "obliviaeDetailId": 1,
        "questStageId": 601291,
        "mission": 6012911,
        "firstClearRewardGroupID": 805,
        "clearRewardGroupID": 806,
        "releaseConditionQuest": 601281,
        "targetCommunicationGroup": 1,
        "targetCommunicationGroupCount": 10,
        "bossIcon": false
    },
    {
        "ID": 601301,
        "questType": 3,
        "obliviaeDetailId": 1,
        "questStageId": 601301,
        "mission": 6013011,
        "firstClearRewardGroupID": 807,
        "clearRewardGroupID": 808,
        "releaseConditionQuest": 601291,
        "targetCommunicationGroup": 1,
        "targetCommunicationGroupCount": 10,
        "bossIcon": true
    },
    {
        "ID": 602011,
        "questType": 3,
        "obliviaeDetailId": 3,
        "questStageId": 602011,
        "mission": 6020111,
        "firstClearRewardGroupID": 809,
        "clearRewardGroupID": 810,
        "releaseConditionQuest": 0,
        "targetCommunicationGroup": 0,
        "targetCommunicationGroupCount": 0,
        "bossIcon": false
    },
    {
        "ID": 602021,
        "questType": 3,
        "obliviaeDetailId": 3,
        "questStageId": 602021,
        "mission": 6020211,
        "firstClearRewardGroupID": 811,
        "clearRewardGroupID": 812,
        "releaseConditionQuest": 602011,
        "targetCommunicationGroup": 0,
        "targetCommunicationGroupCount": 0,
        "bossIcon": false
    },
    {
        "ID": 602031,
        "questType": 3,
        "obliviaeDetailId": 3,
        "questStageId": 602031,
        "mission": 6020311,
        "firstClearRewardGroupID": 813,
        "clearRewardGroupID": 814,
        "releaseConditionQuest": 602021,
        "targetCommunicationGroup": 0,
        "targetCommunicationGroupCount": 0,
        "bossIcon": false
    },
    {
        "ID": 602041,
        "questType": 3,
        "obliviaeDetailId": 3,
        "questStageId": 602041,
        "mission": 6020411,
        "firstClearRewardGroupID": 815,
        "clearRewardGroupID": 816,
        "releaseConditionQuest": 602031,
        "targetCommunicationGroup": 0,
        "targetCommunicationGroupCount": 0,
        "bossIcon": false
    },
    {
        "ID": 602051,
        "questType": 3,
        "obliviaeDetailId": 3,
        "questStageId": 602051,
        "mission": 6020511,
        "firstClearRewardGroupID": 817,
        "clearRewardGroupID": 818,
        "releaseConditionQuest": 602041,
        "targetCommunicationGroup": 0,
        "targetCommunicationGroupCount": 0,
        "bossIcon": true
    },
    {
        "ID": 602061,
        "questType": 3,
        "obliviaeDetailId": 3,
        "questStageId": 602061,
        "mission": 6020611,
        "firstClearRewardGroupID": 819,
        "clearRewardGroupID": 820,
        "releaseConditionQuest": 602051,
        "targetCommunicationGroup": 0,
        "targetCommunicationGroupCount": 0,
        "bossIcon": false
    },
    {
        "ID": 602071,
        "questType": 3,
        "obliviaeDetailId": 3,
        "questStageId": 602071,
        "mission": 6020711,
        "firstClearRewardGroupID": 821,
        "clearRewardGroupID": 822,
        "releaseConditionQuest": 602061,
        "targetCommunicationGroup": 0,
        "targetCommunicationGroupCount": 0,
        "bossIcon": false
    },
    {
        "ID": 602081,
        "questType": 3,
        "obliviaeDetailId": 3,
        "questStageId": 602081,
        "mission": 6020811,
        "firstClearRewardGroupID": 823,
        "clearRewardGroupID": 824,
        "releaseConditionQuest": 602071,
        "targetCommunicationGroup": 0,
        "targetCommunicationGroupCount": 0,
        "bossIcon": false
    },
    {
        "ID": 602091,
        "questType": 3,
        "obliviaeDetailId": 3,
        "questStageId": 602091,
        "mission": 6020911,
        "firstClearRewardGroupID": 825,
        "clearRewardGroupID": 826,
        "releaseConditionQuest": 602081,
        "targetCommunicationGroup": 0,
        "targetCommunicationGroupCount": 0,
        "bossIcon": false
    },
    {
        "ID": 602101,
        "questType": 3,
        "obliviaeDetailId": 3,
        "questStageId": 602101,
        "mission": 6021011,
        "firstClearRewardGroupID": 827,
        "clearRewardGroupID": 828,
        "releaseConditionQuest": 602091,
        "targetCommunicationGroup": 0,
        "targetCommunicationGroupCount": 0,
        "bossIcon": true
    },
    {
        "ID": 602111,
        "questType": 3,
        "obliviaeDetailId": 3,
        "questStageId": 602111,
        "mission": 6021111,
        "firstClearRewardGroupID": 829,
        "clearRewardGroupID": 830,
        "releaseConditionQuest": 602101,
        "targetCommunicationGroup": 0,
        "targetCommunicationGroupCount": 0,
        "bossIcon": false
    },
    {
        "ID": 602121,
        "questType": 3,
        "obliviaeDetailId": 3,
        "questStageId": 602121,
        "mission": 6021211,
        "firstClearRewardGroupID": 831,
        "clearRewardGroupID": 832,
        "releaseConditionQuest": 602111,
        "targetCommunicationGroup": 0,
        "targetCommunicationGroupCount": 0,
        "bossIcon": false
    },
    {
        "ID": 602131,
        "questType": 3,
        "obliviaeDetailId": 3,
        "questStageId": 602131,
        "mission": 6021311,
        "firstClearRewardGroupID": 833,
        "clearRewardGroupID": 834,
        "releaseConditionQuest": 602121,
        "targetCommunicationGroup": 0,
        "targetCommunicationGroupCount": 0,
        "bossIcon": false
    },
    {
        "ID": 602141,
        "questType": 3,
        "obliviaeDetailId": 3,
        "questStageId": 602141,
        "mission": 6021411,
        "firstClearRewardGroupID": 835,
        "clearRewardGroupID": 836,
        "releaseConditionQuest": 602131,
        "targetCommunicationGroup": 0,
        "targetCommunicationGroupCount": 0,
        "bossIcon": false
    },
    {
        "ID": 602151,
        "questType": 3,
        "obliviaeDetailId": 3,
        "questStageId": 602151,
        "mission": 6021511,
        "firstClearRewardGroupID": 837,
        "clearRewardGroupID": 838,
        "releaseConditionQuest": 602141,
        "targetCommunicationGroup": 0,
        "targetCommunicationGroupCount": 0,
        "bossIcon": true
    },
    {
        "ID": 602161,
        "questType": 3,
        "obliviaeDetailId": 3,
        "questStageId": 602161,
        "mission": 6021611,
        "firstClearRewardGroupID": 839,
        "clearRewardGroupID": 840,
        "releaseConditionQuest": 602151,
        "targetCommunicationGroup": 3,
        "targetCommunicationGroupCount": 2,
        "bossIcon": false
    },
    {
        "ID": 602171,
        "questType": 3,
        "obliviaeDetailId": 3,
        "questStageId": 602171,
        "mission": 6021711,
        "firstClearRewardGroupID": 841,
        "clearRewardGroupID": 842,
        "releaseConditionQuest": 602161,
        "targetCommunicationGroup": 3,
        "targetCommunicationGroupCount": 2,
        "bossIcon": false
    },
    {
        "ID": 602181,
        "questType": 3,
        "obliviaeDetailId": 3,
        "questStageId": 602181,
        "mission": 6021811,
        "firstClearRewardGroupID": 843,
        "clearRewardGroupID": 844,
        "releaseConditionQuest": 602171,
        "targetCommunicationGroup": 3,
        "targetCommunicationGroupCount": 2,
        "bossIcon": false
    },
    {
        "ID": 602191,
        "questType": 3,
        "obliviaeDetailId": 3,
        "questStageId": 602191,
        "mission": 6021911,
        "firstClearRewardGroupID": 845,
        "clearRewardGroupID": 846,
        "releaseConditionQuest": 602181,
        "targetCommunicationGroup": 3,
        "targetCommunicationGroupCount": 4,
        "bossIcon": false
    },
    {
        "ID": 602201,
        "questType": 3,
        "obliviaeDetailId": 3,
        "questStageId": 602201,
        "mission": 6022011,
        "firstClearRewardGroupID": 847,
        "clearRewardGroupID": 848,
        "releaseConditionQuest": 602191,
        "targetCommunicationGroup": 3,
        "targetCommunicationGroupCount": 4,
        "bossIcon": true
    },
    {
        "ID": 602211,
        "questType": 3,
        "obliviaeDetailId": 3,
        "questStageId": 602211,
        "mission": 6022111,
        "firstClearRewardGroupID": 849,
        "clearRewardGroupID": 850,
        "releaseConditionQuest": 602201,
        "targetCommunicationGroup": 3,
        "targetCommunicationGroupCount": 4,
        "bossIcon": false
    },
    {
        "ID": 602221,
        "questType": 3,
        "obliviaeDetailId": 3,
        "questStageId": 602221,
        "mission": 6022211,
        "firstClearRewardGroupID": 851,
        "clearRewardGroupID": 852,
        "releaseConditionQuest": 602211,
        "targetCommunicationGroup": 3,
        "targetCommunicationGroupCount": 6,
        "bossIcon": false
    },
    {
        "ID": 602231,
        "questType": 3,
        "obliviaeDetailId": 3,
        "questStageId": 602231,
        "mission": 6022311,
        "firstClearRewardGroupID": 853,
        "clearRewardGroupID": 854,
        "releaseConditionQuest": 602221,
        "targetCommunicationGroup": 3,
        "targetCommunicationGroupCount": 6,
        "bossIcon": false
    },
    {
        "ID": 602241,
        "questType": 3,
        "obliviaeDetailId": 3,
        "questStageId": 602241,
        "mission": 6022411,
        "firstClearRewardGroupID": 855,
        "clearRewardGroupID": 856,
        "releaseConditionQuest": 602231,
        "targetCommunicationGroup": 3,
        "targetCommunicationGroupCount": 6,
        "bossIcon": false
    },
    {
        "ID": 602251,
        "questType": 3,
        "obliviaeDetailId": 3,
        "questStageId": 602251,
        "mission": 6022511,
        "firstClearRewardGroupID": 857,
        "clearRewardGroupID": 858,
        "releaseConditionQuest": 602241,
        "targetCommunicationGroup": 3,
        "targetCommunicationGroupCount": 8,
        "bossIcon": true
    },
    {
        "ID": 602261,
        "questType": 3,
        "obliviaeDetailId": 3,
        "questStageId": 602261,
        "mission": 6022611,
        "firstClearRewardGroupID": 859,
        "clearRewardGroupID": 860,
        "releaseConditionQuest": 602251,
        "targetCommunicationGroup": 3,
        "targetCommunicationGroupCount": 8,
        "bossIcon": false
    },
    {
        "ID": 602271,
        "questType": 3,
        "obliviaeDetailId": 3,
        "questStageId": 602271,
        "mission": 6022711,
        "firstClearRewardGroupID": 861,
        "clearRewardGroupID": 862,
        "releaseConditionQuest": 602261,
        "targetCommunicationGroup": 3,
        "targetCommunicationGroupCount": 8,
        "bossIcon": false
    },
    {
        "ID": 602281,
        "questType": 3,
        "obliviaeDetailId": 3,
        "questStageId": 602281,
        "mission": 6022811,
        "firstClearRewardGroupID": 863,
        "clearRewardGroupID": 864,
        "releaseConditionQuest": 602271,
        "targetCommunicationGroup": 3,
        "targetCommunicationGroupCount": 10,
        "bossIcon": false
    },
    {
        "ID": 602291,
        "questType": 3,
        "obliviaeDetailId": 3,
        "questStageId": 602291,
        "mission": 6022911,
        "firstClearRewardGroupID": 865,
        "clearRewardGroupID": 866,
        "releaseConditionQuest": 602281,
        "targetCommunicationGroup": 3,
        "targetCommunicationGroupCount": 10,
        "bossIcon": false
    },
    {
        "ID": 602301,
        "questType": 3,
        "obliviaeDetailId": 3,
        "questStageId": 602301,
        "mission": 6023011,
        "firstClearRewardGroupID": 867,
        "clearRewardGroupID": 868,
        "releaseConditionQuest": 602291,
        "targetCommunicationGroup": 3,
        "targetCommunicationGroupCount": 10,
        "bossIcon": true
    },
    {
        "ID": 603011,
        "questType": 3,
        "obliviaeDetailId": 2,
        "questStageId": 603011,
        "mission": 6030111,
        "firstClearRewardGroupID": 869,
        "clearRewardGroupID": 870,
        "releaseConditionQuest": 0,
        "targetCommunicationGroup": 0,
        "targetCommunicationGroupCount": 0,
        "bossIcon": false
    },
    {
        "ID": 603021,
        "questType": 3,
        "obliviaeDetailId": 2,
        "questStageId": 603021,
        "mission": 6030211,
        "firstClearRewardGroupID": 871,
        "clearRewardGroupID": 872,
        "releaseConditionQuest": 603011,
        "targetCommunicationGroup": 0,
        "targetCommunicationGroupCount": 0,
        "bossIcon": false
    },
    {
        "ID": 603031,
        "questType": 3,
        "obliviaeDetailId": 2,
        "questStageId": 603031,
        "mission": 6030311,
        "firstClearRewardGroupID": 873,
        "clearRewardGroupID": 874,
        "releaseConditionQuest": 603021,
        "targetCommunicationGroup": 0,
        "targetCommunicationGroupCount": 0,
        "bossIcon": false
    },
    {
        "ID": 603041,
        "questType": 3,
        "obliviaeDetailId": 2,
        "questStageId": 603041,
        "mission": 6030411,
        "firstClearRewardGroupID": 875,
        "clearRewardGroupID": 876,
        "releaseConditionQuest": 603031,
        "targetCommunicationGroup": 0,
        "targetCommunicationGroupCount": 0,
        "bossIcon": false
    },
    {
        "ID": 603051,
        "questType": 3,
        "obliviaeDetailId": 2,
        "questStageId": 603051,
        "mission": 6030511,
        "firstClearRewardGroupID": 877,
        "clearRewardGroupID": 878,
        "releaseConditionQuest": 603041,
        "targetCommunicationGroup": 0,
        "targetCommunicationGroupCount": 0,
        "bossIcon": true
    },
    {
        "ID": 603061,
        "questType": 3,
        "obliviaeDetailId": 2,
        "questStageId": 603061,
        "mission": 6030611,
        "firstClearRewardGroupID": 879,
        "clearRewardGroupID": 880,
        "releaseConditionQuest": 603051,
        "targetCommunicationGroup": 0,
        "targetCommunicationGroupCount": 0,
        "bossIcon": false
    },
    {
        "ID": 603071,
        "questType": 3,
        "obliviaeDetailId": 2,
        "questStageId": 603071,
        "mission": 6030711,
        "firstClearRewardGroupID": 881,
        "clearRewardGroupID": 882,
        "releaseConditionQuest": 603061,
        "targetCommunicationGroup": 0,
        "targetCommunicationGroupCount": 0,
        "bossIcon": false
    },
    {
        "ID": 603081,
        "questType": 3,
        "obliviaeDetailId": 2,
        "questStageId": 603081,
        "mission": 6030811,
        "firstClearRewardGroupID": 883,
        "clearRewardGroupID": 884,
        "releaseConditionQuest": 603071,
        "targetCommunicationGroup": 0,
        "targetCommunicationGroupCount": 0,
        "bossIcon": false
    },
    {
        "ID": 603091,
        "questType": 3,
        "obliviaeDetailId": 2,
        "questStageId": 603091,
        "mission": 6030911,
        "firstClearRewardGroupID": 885,
        "clearRewardGroupID": 886,
        "releaseConditionQuest": 603081,
        "targetCommunicationGroup": 0,
        "targetCommunicationGroupCount": 0,
        "bossIcon": false
    },
    {
        "ID": 603101,
        "questType": 3,
        "obliviaeDetailId": 2,
        "questStageId": 603101,
        "mission": 6031011,
        "firstClearRewardGroupID": 887,
        "clearRewardGroupID": 888,
        "releaseConditionQuest": 603091,
        "targetCommunicationGroup": 0,
        "targetCommunicationGroupCount": 0,
        "bossIcon": true
    },
    {
        "ID": 603111,
        "questType": 3,
        "obliviaeDetailId": 2,
        "questStageId": 603111,
        "mission": 6031111,
        "firstClearRewardGroupID": 889,
        "clearRewardGroupID": 890,
        "releaseConditionQuest": 603101,
        "targetCommunicationGroup": 0,
        "targetCommunicationGroupCount": 0,
        "bossIcon": false
    },
    {
        "ID": 603121,
        "questType": 3,
        "obliviaeDetailId": 2,
        "questStageId": 603121,
        "mission": 6031211,
        "firstClearRewardGroupID": 891,
        "clearRewardGroupID": 892,
        "releaseConditionQuest": 603111,
        "targetCommunicationGroup": 0,
        "targetCommunicationGroupCount": 0,
        "bossIcon": false
    },
    {
        "ID": 603131,
        "questType": 3,
        "obliviaeDetailId": 2,
        "questStageId": 603131,
        "mission": 6031311,
        "firstClearRewardGroupID": 893,
        "clearRewardGroupID": 894,
        "releaseConditionQuest": 603121,
        "targetCommunicationGroup": 0,
        "targetCommunicationGroupCount": 0,
        "bossIcon": false
    },
    {
        "ID": 603141,
        "questType": 3,
        "obliviaeDetailId": 2,
        "questStageId": 603141,
        "mission": 6031411,
        "firstClearRewardGroupID": 895,
        "clearRewardGroupID": 896,
        "releaseConditionQuest": 603131,
        "targetCommunicationGroup": 0,
        "targetCommunicationGroupCount": 0,
        "bossIcon": false
    },
    {
        "ID": 603151,
        "questType": 3,
        "obliviaeDetailId": 2,
        "questStageId": 603151,
        "mission": 6031511,
        "firstClearRewardGroupID": 897,
        "clearRewardGroupID": 898,
        "releaseConditionQuest": 603141,
        "targetCommunicationGroup": 0,
        "targetCommunicationGroupCount": 0,
        "bossIcon": true
    },
    {
        "ID": 603161,
        "questType": 3,
        "obliviaeDetailId": 2,
        "questStageId": 603161,
        "mission": 6031611,
        "firstClearRewardGroupID": 899,
        "clearRewardGroupID": 900,
        "releaseConditionQuest": 603151,
        "targetCommunicationGroup": 2,
        "targetCommunicationGroupCount": 2,
        "bossIcon": false
    },
    {
        "ID": 603171,
        "questType": 3,
        "obliviaeDetailId": 2,
        "questStageId": 603171,
        "mission": 6031711,
        "firstClearRewardGroupID": 901,
        "clearRewardGroupID": 902,
        "releaseConditionQuest": 603161,
        "targetCommunicationGroup": 2,
        "targetCommunicationGroupCount": 2,
        "bossIcon": false
    },
    {
        "ID": 603181,
        "questType": 3,
        "obliviaeDetailId": 2,
        "questStageId": 603181,
        "mission": 6031811,
        "firstClearRewardGroupID": 903,
        "clearRewardGroupID": 904,
        "releaseConditionQuest": 603171,
        "targetCommunicationGroup": 2,
        "targetCommunicationGroupCount": 2,
        "bossIcon": false
    },
    {
        "ID": 603191,
        "questType": 3,
        "obliviaeDetailId": 2,
        "questStageId": 603191,
        "mission": 6031911,
        "firstClearRewardGroupID": 905,
        "clearRewardGroupID": 906,
        "releaseConditionQuest": 603181,
        "targetCommunicationGroup": 2,
        "targetCommunicationGroupCount": 4,
        "bossIcon": false
    },
    {
        "ID": 603201,
        "questType": 3,
        "obliviaeDetailId": 2,
        "questStageId": 603201,
        "mission": 6032011,
        "firstClearRewardGroupID": 907,
        "clearRewardGroupID": 908,
        "releaseConditionQuest": 603191,
        "targetCommunicationGroup": 2,
        "targetCommunicationGroupCount": 4,
        "bossIcon": true
    },
    {
        "ID": 603211,
        "questType": 3,
        "obliviaeDetailId": 2,
        "questStageId": 603211,
        "mission": 6032111,
        "firstClearRewardGroupID": 909,
        "clearRewardGroupID": 910,
        "releaseConditionQuest": 603201,
        "targetCommunicationGroup": 2,
        "targetCommunicationGroupCount": 4,
        "bossIcon": false
    },
    {
        "ID": 603221,
        "questType": 3,
        "obliviaeDetailId": 2,
        "questStageId": 603221,
        "mission": 6032211,
        "firstClearRewardGroupID": 911,
        "clearRewardGroupID": 912,
        "releaseConditionQuest": 603211,
        "targetCommunicationGroup": 2,
        "targetCommunicationGroupCount": 6,
        "bossIcon": false
    },
    {
        "ID": 603231,
        "questType": 3,
        "obliviaeDetailId": 2,
        "questStageId": 603231,
        "mission": 6032311,
        "firstClearRewardGroupID": 913,
        "clearRewardGroupID": 914,
        "releaseConditionQuest": 603221,
        "targetCommunicationGroup": 2,
        "targetCommunicationGroupCount": 6,
        "bossIcon": false
    },
    {
        "ID": 603241,
        "questType": 3,
        "obliviaeDetailId": 2,
        "questStageId": 603241,
        "mission": 6032411,
        "firstClearRewardGroupID": 915,
        "clearRewardGroupID": 916,
        "releaseConditionQuest": 603231,
        "targetCommunicationGroup": 2,
        "targetCommunicationGroupCount": 6,
        "bossIcon": false
    },
    {
        "ID": 603251,
        "questType": 3,
        "obliviaeDetailId": 2,
        "questStageId": 603251,
        "mission": 6032511,
        "firstClearRewardGroupID": 917,
        "clearRewardGroupID": 918,
        "releaseConditionQuest": 603241,
        "targetCommunicationGroup": 2,
        "targetCommunicationGroupCount": 8,
        "bossIcon": true
    },
    {
        "ID": 603261,
        "questType": 3,
        "obliviaeDetailId": 2,
        "questStageId": 603261,
        "mission": 6032611,
        "firstClearRewardGroupID": 919,
        "clearRewardGroupID": 920,
        "releaseConditionQuest": 603251,
        "targetCommunicationGroup": 2,
        "targetCommunicationGroupCount": 8,
        "bossIcon": false
    },
    {
        "ID": 603271,
        "questType": 3,
        "obliviaeDetailId": 2,
        "questStageId": 603271,
        "mission": 6032711,
        "firstClearRewardGroupID": 921,
        "clearRewardGroupID": 922,
        "releaseConditionQuest": 603261,
        "targetCommunicationGroup": 2,
        "targetCommunicationGroupCount": 8,
        "bossIcon": false
    },
    {
        "ID": 603281,
        "questType": 3,
        "obliviaeDetailId": 2,
        "questStageId": 603281,
        "mission": 6032811,
        "firstClearRewardGroupID": 923,
        "clearRewardGroupID": 924,
        "releaseConditionQuest": 603271,
        "targetCommunicationGroup": 2,
        "targetCommunicationGroupCount": 10,
        "bossIcon": false
    },
    {
        "ID": 603291,
        "questType": 3,
        "obliviaeDetailId": 2,
        "questStageId": 603291,
        "mission": 6032911,
        "firstClearRewardGroupID": 925,
        "clearRewardGroupID": 926,
        "releaseConditionQuest": 603281,
        "targetCommunicationGroup": 2,
        "targetCommunicationGroupCount": 10,
        "bossIcon": false
    },
    {
        "ID": 603301,
        "questType": 3,
        "obliviaeDetailId": 2,
        "questStageId": 603301,
        "mission": 6033011,
        "firstClearRewardGroupID": 927,
        "clearRewardGroupID": 928,
        "releaseConditionQuest": 603291,
        "targetCommunicationGroup": 2,
        "targetCommunicationGroupCount": 10,
        "bossIcon": true
    }
]